counterpy/__init__.py
counterpy/cantus.py
counterpy/functions.py
counterpy/voice.py
harmonics/__init__.py
harmonics/__main__.py
harmonics/audio.py
harmonics/bot.py
harmonics/harmonics.py
harmonics/midi.py
harmonics-0.0.0.dist-info/LICENCE.txt
harmonics-0.0.0.dist-info/METADATA
harmonics-0.0.0.dist-info/WHEEL
harmonics-0.0.0.dist-info/top_level.txt
harmonics-0.0.0.dist-info/RECORD
